click_utils-0.2.1.dist-info/METADATA
click_utils-0.2.1.dist-info/top_level.txt
click_utils-0.2.1.dist-info/metadata.json
click_utils-0.2.1.dist-info/RECORD
click_utils-0.2.1.dist-info/WHEEL
click_utils-0.2.1.dist-info/DESCRIPTION.rst
click_utils/__init__.py
click_utils/defaults.py
click_utils/help.py
click_utils/logging.py
