Metadata-Version: 2.0
Name: click-utils
Version: 0.2.1
Summary: a set of utilites for writing command line programs with Click
Home-page: https://github.com/slafs/click-utils
Author: Sławek Ehlert
Author-email: slafs.e@gmail.com
License: BSD
Keywords: click-utils
Platform: UNKNOWN
Classifier: Development Status :: 2 - Pre-Alpha
Classifier: Intended Audience :: Developers
Classifier: License :: OSI Approved :: BSD License
Classifier: Natural Language :: English
Classifier: Programming Language :: Python :: 2
Classifier: Programming Language :: Python :: 2.6
Classifier: Programming Language :: Python :: 2.7
Classifier: Programming Language :: Python :: 3
Classifier: Programming Language :: Python :: 3.3
Classifier: Programming Language :: Python :: 3.4
Requires-Dist: Click (>=3.0,<4.0)
